./.gitignore
./GEMINI_SETUP.md
./MULTI_MODEL_SETUP.md
./PKG-INFO
./README.en.md
./README.md
./cli.py
./main.py
./pyproject.toml
./api/__init__.py
./api/agent.py
./api/mcp.py
./core/apps/agents/abc.py
./core/apps/agents/base.py
./core/apps/builder/builder.py
./core/apps/mcp/__init__.py
./core/apps/mcp/client.py
./core/apps/mcp/loader.py
./core/apps/mcp/mcp_tool.json
./core/apps/model/base.py
./core/apps/observability/langsmith.py
./core/apps/tools/__init__.py
./core/apps/tools/my_tools.py
./core/apps/tools/tools.py
./core/apps/utils/dict.py
./core/models/__init__.py
./core/models/agent.py
./core/models/request.py
./core/models/response.py
./lib/agimat_client.py
./lib/config.py
./lib/drawing.py
./lib/env_loader.py
./lib/http_client.py
./lib/llm_provider.py
./lib/revit.py
./lib/prompt/drawing.md
./lib/prompt/revit.md
./ui/ui.py
agimat_agent-0.1.9.dist-info/METADATA
agimat_agent-0.1.9.dist-info/WHEEL
agimat_agent-0.1.9.dist-info/entry_points.txt
agimat_agent-0.1.9.dist-info/RECORD
