Metadata-Version: 2.4
Name: agimat-agent
Version: 0.1.9
Summary: 基于 FastAPI 和 LangGraph 的智能代理管理平台
Project-URL: Homepage, https://github.com/your-username/agimat-agent
Project-URL: Repository, https://github.com/your-username/agimat-agent
Project-URL: Documentation, https://github.com/your-username/agimat-agent#readme
Author-email: Your Name <your.email@example.com>
License: MIT
Keywords: agent,ai,fastapi,langchain,mcp
Classifier: Development Status :: 3 - Alpha
Classifier: Intended Audience :: Developers
Classifier: License :: OSI Approved :: MIT License
Classifier: Programming Language :: Python :: 3
Classifier: Programming Language :: Python :: 3.12
Requires-Python: >=3.12
Requires-Dist: aiofiles
Requires-Dist: aiohttp
Requires-Dist: build>=1.2.2.post1
Requires-Dist: email-validator
Requires-Dist: fastapi
Requires-Dist: fastmcp
Requires-Dist: google-generativeai
Requires-Dist: jinja2
Requires-Dist: langchain
Requires-Dist: langchain-anthropic
Requires-Dist: langchain-community
Requires-Dist: langchain-core
Requires-Dist: langchain-experimental
Requires-Dist: langchain-google-genai
Requires-Dist: langchain-mcp-adapters
Requires-Dist: langchain-openai
Requires-Dist: langchain-tavily
Requires-Dist: langgraph
Requires-Dist: langsmith
Requires-Dist: mcp
Requires-Dist: motor
Requires-Dist: openai
Requires-Dist: passlib[bcrypt]
Requires-Dist: psutil
Requires-Dist: pydantic
Requires-Dist: pydantic-settings
Requires-Dist: python-dateutil
Requires-Dist: python-dotenv
Requires-Dist: python-jose[cryptography]
Requires-Dist: python-multipart
Requires-Dist: pytz
Requires-Dist: pyyaml
Requires-Dist: requests
Requires-Dist: streamlit>=1.28.0
Requires-Dist: tenacity
Requires-Dist: twine>=6.1.0
Requires-Dist: uvicorn
Requires-Dist: wavespeed-mcp>=0.1.6
Provides-Extra: dev
Requires-Dist: black>=24.1.1; extra == 'dev'
Requires-Dist: flake8>=7.0.0; extra == 'dev'
Requires-Dist: httpx>=0.27; extra == 'dev'
Requires-Dist: isort>=5.13.2; extra == 'dev'
Requires-Dist: mypy>=1.8.0; extra == 'dev'
Requires-Dist: pytest-asyncio>=0.23.5; extra == 'dev'
Requires-Dist: pytest>=8.0.0; extra == 'dev'
